{"entity": "Age", "ruleScope": "sentence", "matchScope": "token", "regex": "\\s*(0?[1-9]|[1-9][0-9]|[1][1-9][1-9]|200){1,2}[\\s-,]+|(?i)\\b(?:zero|ten|eleven|twelve|thirteen|fourteen|fifteen|sixteen|seventeen|eighteen|nineteen|twenty)\\b(?=\\s*year)|\\b(?:(?:one|two|three|four|five|six|seven|eight|nine)? hundred(?:\\sand)?\\s)?(?:(?:twenty|thirty|forty|fifty|sixty|seventy|eighty|ninety)[\\s-]?)?\\b(?:one|two|three|four|five|six|seven|eight|nine)?(?=\\syear)", "prefix": ["age of"], "suffix": ["-years-old", "years-old", "-year-old", "-months-old", "-month-old", "-months-old", "-day-old", "-days-old", "month old", "days old", "year old", "years old", "years", "year", "months", "old"], "contextLength": 25, "context": [], "contextException": ["ago"], "exceptionDistance": 10}